Workbook

Sheet Dashboard
A1: Futures Trading Academy — Journal Dashboard | B1: Futures Trading Academy — Journal Dashboard | C1: Futures Trading Academy — Journal Dashboard | D1: Futures Trading Academy — Journal Dashboard | E1: Futures Trading Academy — Journal Dashboard | F1: Futures Trading Academy — Journal Dashboard | G1: Futures Trading Academy — Journal Dashboard | H1: Futures Trading Academy — Journal Dashboard
A2: Version 1.0 • Formula-driven tracker • Blank metrics are expected until observations and trades are entered | B2: Version 1.0 • Formula-driven tracker • Blank metrics are expected until observations and trades are entered | C2: Version 1.0 • Formula-driven tracker • Blank metrics are expected until observations and trades are entered | D2: Version 1.0 • Formula-driven tracker • Blank metrics are expected until observations and trades are entered | E2: Version 1.0 • Formula-driven tracker • Blank metrics are expected until observations and trades are entered | F2: Version 1.0 • Formula-driven tracker • Blank metrics are expected until observations and trades are entered | G2: Version 1.0 • Formula-driven tracker • Blank metrics are expected until observations and trades are entered | H2: Version 1.0 • Formula-driven tracker • Blank metrics are expected until observations and trades are entered
A4: Risk Inputs | B4: Risk Inputs | D4: Trade Metrics | E4: Trade Metrics | G4: Evidence Counts | H4: Evidence Counts
A5: Reference account (USD) | B5: 10000 | D5: Total trades | E5: =COUNT(Trades!$B$6:$B$205) -> 0 | G5: Included backtest cases | H5: =COUNTIF(Backtest!$X$6:$X$205,"Yes") -> 0
A6: Maximum risk % | B6: 0.0025 | D6: Net P&L | E6: =SUM(Trades!$X$6:$X$205) -> 0 | G6: Out-of-sample cases | H6: =COUNTIFS(Backtest!$E$6:$E$205,"Out-of-sample",Backtest!$X$6:$X$205,"Yes") -> 0
A7: Maximum risk $ | B7: =B5*B6 -> 25 | D7: Net R | E7: =SUM(Trades!$Z$6:$Z$205) -> 0 | G7: Replay-sim trades | H7: =COUNTIF(Trades!$C$6:$C$205,"Replay Sim") -> 0
A8: Daily stop (R) | B8: 2 | D8: Win rate | E8: =IF(E5=0,"",COUNTIF(Trades!$Z$6:$Z$205,">0")/E5) | G8: Forward server-sim trades | H8: =COUNTIF(Trades!$C$6:$C$205,"Server Sim") -> 0
A9: Weekly stop (R) | B9: 5 | D9: Average R | E9: =IF(E5=0,"",E7/E5) | G9: Recorded observations | H9: =COUNT(Observations!$B$6:$B$205) -> 0
A10: Strategy drawdown stop (R) | B10: 7.5 | D10: Profit factor | E10: =IF(ABS(SUMIF(Trades!$Z$6:$Z$205,"<0",Trades!$Z$6:$Z$205))=0,"",SUMIF(Trades!$Z$6:$Z$205,">0",Trades!$Z$6:$Z$205)/ABS(SUMIF(Trades!$Z$6:$Z$205,"<0",Trades!$Z$6:$Z$205))) | G10: Study hours | H10: =SUMIFS('Study Log'!$I$6:$I$205,'Study Log'!$A$6:$A$205,"<>EXAMPLE-001")/60 -> 21.666667
A11: Current curriculum week | B11: 1 | D11: Maximum drawdown (R) | E11: =IF(E5=0,"",ABS(MIN(Trades!$AL$6:$AL$205))) | G11: Curriculum status | H11: Week 1 — Ready
D12: Plan compliance | E12: =IF(E5=0,"",COUNTIF(Trades!$AC$6:$AC$205,"Yes")/E5)
D13: Hard-rule breaches | E13: =COUNTIF(Trades!$AE$6:$AE$205,"Yes") -> 0
A14: Gate Targets | B14: Gate Targets | C14: Gate Targets | D14: Gate Targets | E14: Gate Targets | F14: Gate Targets | G14: Gate Targets | H14: Gate Targets
A15: Gate | B15: Status | C15: Primary evidence | D15: Current | E15: Target | F15: Hard-risk condition | G15: Decision | H15: Notes
A16: Foundation | B16: Not attempted | C16: Concept + platform safety | E16: 85% exam | F16: Zero live orders | G16: Repeat until passed | H16: Week 4
A17: Profile | B17: Not attempted | C17: Reviewed sessions | D17: 0 | E17: 20 | F17: No hindsight edits | G17: Repeat until passed | H17: Week 8
A18: Order Flow | B18: Not attempted | C18: Blinded sequences | D18: 0 | E18: 30 | F18: Definitions locked | G18: Repeat until passed | H18: Week 12
A19: Edge Evidence | B19: Not attempted | C19: Historical/OOS cases | D19: 0 | E19: 100 + 30 OOS | F19: No OOS rule changes | G19: Reject/revise/advance | H19: Week 16
A20: Simulation | B20: Not attempted | C20: Forward trades/sessions | D20: 0 | E20: 60 / 30 | F20: 100% hard-risk | G20: Repeat until passed | H20: Week 20+
A21: Final | B21: Not attempted | C21: Complete portfolio | D21: 0 | E21: All prior gates | F21: Separate live decision | G21: Three-option decision | H21: Week 24+
A23: Safety: Futures are leveraged and high risk. This workbook is a training and record-keeping tool, not a profitability forecast or live-trading authorization. Stop if the account mode, contract, data, or order state is uncertain. | B23: Safety: Futures are leveraged and high risk. This workbook is a training and record-keeping tool, not a profitability forecast or live-trading authorization. Stop if the account mode, contract, data, or order state is uncertain. | C23: Safety: Futures are leveraged and high risk. This workbook is a training and record-keeping tool, not a profitability forecast or live-trading authorization. Stop if the account mode, contract, data, or order state is uncertain. | D23: Safety: Futures are leveraged and high risk. This workbook is a training and record-keeping tool, not a profitability forecast or live-trading authorization. Stop if the account mode, contract, data, or order state is uncertain. | E23: Safety: Futures are leveraged and high risk. This workbook is a training and record-keeping tool, not a profitability forecast or live-trading authorization. Stop if the account mode, contract, data, or order state is uncertain. | F23: Safety: Futures are leveraged and high risk. This workbook is a training and record-keeping tool, not a profitability forecast or live-trading authorization. Stop if the account mode, contract, data, or order state is uncertain. | G23: Safety: Futures are leveraged and high risk. This workbook is a training and record-keeping tool, not a profitability forecast or live-trading authorization. Stop if the account mode, contract, data, or order state is uncertain. | H23: Safety: Futures are leveraged and high risk. This workbook is a training and record-keeping tool, not a profitability forecast or live-trading authorization. Stop if the account mode, contract, data, or order state is uncertain.
A24: Safety: Futures are leveraged and high risk. This workbook is a training and record-keeping tool, not a profitability forecast or live-trading authorization. Stop if the account mode, contract, data, or order state is uncertain. | B24: Safety: Futures are leveraged and high risk. This workbook is a training and record-keeping tool, not a profitability forecast or live-trading authorization. Stop if the account mode, contract, data, or order state is uncertain. | C24: Safety: Futures are leveraged and high risk. This workbook is a training and record-keeping tool, not a profitability forecast or live-trading authorization. Stop if the account mode, contract, data, or order state is uncertain. | D24: Safety: Futures are leveraged and high risk. This workbook is a training and record-keeping tool, not a profitability forecast or live-trading authorization. Stop if the account mode, contract, data, or order state is uncertain. | E24: Safety: Futures are leveraged and high risk. This workbook is a training and record-keeping tool, not a profitability forecast or live-trading authorization. Stop if the account mode, contract, data, or order state is uncertain. | F24: Safety: Futures are leveraged and high risk. This workbook is a training and record-keeping tool, not a profitability forecast or live-trading authorization. Stop if the account mode, contract, data, or order state is uncertain. | G24: Safety: Futures are leveraged and high risk. This workbook is a training and record-keeping tool, not a profitability forecast or live-trading authorization. Stop if the account mode, contract, data, or order state is uncertain. | H24: Safety: Futures are leveraged and high risk. This workbook is a training and record-keeping tool, not a profitability forecast or live-trading authorization. Stop if the account mode, contract, data, or order state is uncertain.
A25: Safety: Futures are leveraged and high risk. This workbook is a training and record-keeping tool, not a profitability forecast or live-trading authorization. Stop if the account mode, contract, data, or order state is uncertain. | B25: Safety: Futures are leveraged and high risk. This workbook is a training and record-keeping tool, not a profitability forecast or live-trading authorization. Stop if the account mode, contract, data, or order state is uncertain. | C25: Safety: Futures are leveraged and high risk. This workbook is a training and record-keeping tool, not a profitability forecast or live-trading authorization. Stop if the account mode, contract, data, or order state is uncertain. | D25: Safety: Futures are leveraged and high risk. This workbook is a training and record-keeping tool, not a profitability forecast or live-trading authorization. Stop if the account mode, contract, data, or order state is uncertain. | E25: Safety: Futures are leveraged and high risk. This workbook is a training and record-keeping tool, not a profitability forecast or live-trading authorization. Stop if the account mode, contract, data, or order state is uncertain. | F25: Safety: Futures are leveraged and high risk. This workbook is a training and record-keeping tool, not a profitability forecast or live-trading authorization. Stop if the account mode, contract, data, or order state is uncertain. | G25: Safety: Futures are leveraged and high risk. This workbook is a training and record-keeping tool, not a profitability forecast or live-trading authorization. Stop if the account mode, contract, data, or order state is uncertain. | H25: Safety: Futures are leveraged and high risk. This workbook is a training and record-keeping tool, not a profitability forecast or live-trading authorization. Stop if the account mode, contract, data, or order state is uncertain.

Sheet Trades
A1: Trade Journal | B1: Trade Journal | C1: Trade Journal | D1: Trade Journal | E1: Trade Journal | F1: Trade Journal | G1: Trade Journal | H1: Trade Journal | I1: Trade Journal | J1: Trade Journal | K1: Trade Journal | L1: Trade Journal | M1: Trade Journal | N1: Trade Journal | O1: Trade Journal | P1: Trade Journal | Q1: Trade Journal | R1: Trade Journal | S1: Trade Journal | T1: Trade Journal | U1: Trade Journal | V1: Trade Journal | W1: Trade Journal | X1: Trade Journal | Y1: Trade Journal | Z1: Trade Journal | AA1: Trade Journal | AB1: Trade Journal | AC1: Trade Journal | AD1: Trade Journal | AE1: Trade Journal | AF1: Trade Journal | AG1: Trade Journal | AH1: Trade Journal | AI1: Trade Journal | AJ1: Trade Journal | AK1: Trade Journal | AL1: Trade Journal
A2: Blue text = user input • Gray columns = formulas • Use only one row per completed trade • Rows 6–205 are ready | B2: Blue text = user input • Gray columns = formulas • Use only one row per completed trade • Rows 6–205 are ready | C2: Blue text = user input • Gray columns = formulas • Use only one row per completed trade • Rows 6–205 are ready | D2: Blue text = user input • Gray columns = formulas • Use only one row per completed trade • Rows 6–205 are ready | E2: Blue text = user input • Gray columns = formulas • Use only one row per completed trade • Rows 6–205 are ready | F2: Blue text = user input • Gray columns = formulas • Use only one row per completed trade • Rows 6–205 are ready | G2: Blue text = user input • Gray columns = formulas • Use only one row per completed trade • Rows 6–205 are ready | H2: Blue text = user input • Gray columns = formulas • Use only one row per completed trade • Rows 6–205 are ready | I2: Blue text = user input • Gray columns = formulas • Use only one row per completed trade • Rows 6–205 are ready | J2: Blue text = user input • Gray columns = formulas • Use only one row per completed trade • Rows 6–205 are ready | K2: Blue text = user input • Gray columns = formulas • Use only one row per completed trade • Rows 6–205 are ready | L2: Blue text = user input • Gray columns = formulas • Use only one row per completed trade • Rows 6–205 are ready | M2: Blue text = user input • Gray columns = formulas • Use only one row per completed trade • Rows 6–205 are ready | N2: Blue text = user input • Gray columns = formulas • Use only one row per completed trade • Rows 6–205 are ready | O2: Blue text = user input • Gray columns = formulas • Use only one row per completed trade • Rows 6–205 are ready | P2: Blue text = user input • Gray columns = formulas • Use only one row per completed trade • Rows 6–205 are ready | Q2: Blue text = user input • Gray columns = formulas • Use only one row per completed trade • Rows 6–205 are ready | R2: Blue text = user input • Gray columns = formulas • Use only one row per completed trade • Rows 6–205 are ready | S2: Blue text = user input • Gray columns = formulas • Use only one row per completed trade • Rows 6–205 are ready | T2: Blue text = user input • Gray columns = formulas • Use only one row per completed trade • Rows 6–205 are ready | U2: Blue text = user input • Gray columns = formulas • Use only one row per completed trade • Rows 6–205 are ready | V2: Blue text = user input • Gray columns = formulas • Use only one row per completed trade • Rows 6–205 are ready | W2: Blue text = user input • Gray columns = formulas • Use only one row per completed trade • Rows 6–205 are ready | X2: Blue text = user input • Gray columns = formulas • Use only one row per completed trade • Rows 6–205 are ready | Y2: Blue text = user input • Gray columns = formulas • Use only one row per completed trade • Rows 6–205 are ready | Z2: Blue text = user input • Gray columns = formulas • Use only one row per completed trade • Rows 6–205 are ready | AA2: Blue text = user input • Gray columns = formulas • Use only one row per completed trade • Rows 6–205 are ready | AB2: Blue text = user input • Gray columns = formulas • Use only one row per completed trade • Rows 6–205 are ready | AC2: Blue text = user input • Gray columns = formulas • Use only one row per completed trade • Rows 6–205 are ready | AD2: Blue text = user input • Gray columns = formulas • Use only one row per completed trade • Rows 6–205 are ready | AE2: Blue text = user input • Gray columns = formulas • Use only one row per completed trade • Rows 6–205 are ready | AF2: Blue text = user input • Gray columns = formulas • Use only one row per completed trade • Rows 6–205 are ready | AG2: Blue text = user input • Gray columns = formulas • Use only one row per completed trade • Rows 6–205 are ready | AH2: Blue text = user input • Gray columns = formulas • Use only one row per completed trade • Rows 6–205 are ready | AI2: Blue text = user input • Gray columns = formulas • Use only one row per completed trade • Rows 6–205 are ready | AJ2: Blue text = user input • Gray columns = formulas • Use only one row per completed trade • Rows 6–205 are ready | AK2: Blue text = user input • Gray columns = formulas • Use only one row per completed trade • Rows 6–205 are ready | AL2: Blue text = user input • Gray columns = formulas • Use only one row per completed trade • Rows 6–205 are ready
A4: Enter planned risk, execution, process, and evidence. Do not overwrite formula columns S:T, W:Z, or AJ:AL. | B4: Enter planned risk, execution, process, and evidence. Do not overwrite formula columns S:T, W:Z, or AJ:AL. | C4: Enter planned risk, execution, process, and evidence. Do not overwrite formula columns S:T, W:Z, or AJ:AL. | D4: Enter planned risk, execution, process, and evidence. Do not overwrite formula columns S:T, W:Z, or AJ:AL. | E4: Enter planned risk, execution, process, and evidence. Do not overwrite formula columns S:T, W:Z, or AJ:AL. | F4: Enter planned risk, execution, process, and evidence. Do not overwrite formula columns S:T, W:Z, or AJ:AL. | G4: Enter planned risk, execution, process, and evidence. Do not overwrite formula columns S:T, W:Z, or AJ:AL. | H4: Enter planned risk, execution, process, and evidence. Do not overwrite formula columns S:T, W:Z, or AJ:AL. | I4: Enter planned risk, execution, process, and evidence. Do not overwrite formula columns S:T, W:Z, or AJ:AL. | J4: Enter planned risk, execution, process, and evidence. Do not overwrite formula columns S:T, W:Z, or AJ:AL. | K4: Enter planned risk, execution, process, and evidence. Do not overwrite formula columns S:T, W:Z, or AJ:AL. | L4: Enter planned risk, execution, process, and evidence. Do not overwrite formula columns S:T, W:Z, or AJ:AL. | M4: Enter planned risk, execution, process, and evidence. Do not overwrite formula columns S:T, W:Z, or AJ:AL. | N4: Enter planned risk, execution, process, and evidence. Do not overwrite formula columns S:T, W:Z, or AJ:AL. | O4: Enter planned risk, execution, process, and evidence. Do not overwrite formula columns S:T, W:Z, or AJ:AL. | P4: Enter planned risk, execution, process, and evidence. Do not overwrite formula columns S:T, W:Z, or AJ:AL. | Q4: Enter planned risk, execution, process, and evidence. Do not overwrite formula columns S:T, W:Z, or AJ:AL. | R4: Enter planned risk, execution, process, and evidence. Do not overwrite formula columns S:T, W:Z, or AJ:AL. | S4: Enter planned risk, execution, process, and evidence. Do not overwrite formula columns S:T, W:Z, or AJ:AL. | T4: Enter planned risk, execution, process, and evidence. Do not overwrite formula columns S:T, W:Z, or AJ:AL. | U4: Enter planned risk, execution, process, and evidence. Do not overwrite formula columns S:T, W:Z, or AJ:AL. | V4: Enter planned risk, execution, process, and evidence. Do not overwrite formula columns S:T, W:Z, or AJ:AL. | W4: Enter planned risk, execution, process, and evidence. Do not overwrite formula columns S:T, W:Z, or AJ:AL. | X4: Enter planned risk, execution, process, and evidence. Do not overwrite formula columns S:T, W:Z, or AJ:AL. | Y4: Enter planned risk, execution, process, and evidence. Do not overwrite formula columns S:T, W:Z, or AJ:AL. | Z4: Enter planned risk, execution, process, and evidence. Do not overwrite formula columns S:T, W:Z, or AJ:AL. | AA4: Enter planned risk, execution, process, and evidence. Do not overwrite formula columns S:T, W:Z, or AJ:AL. | AB4: Enter planned risk, execution, process, and evidence. Do not overwrite formula columns S:T, W:Z, or AJ:AL. | AC4: Enter planned risk, execution, process, and evidence. Do not overwrite formula columns S:T, W:Z, or AJ:AL. | AD4: Enter planned risk, execution, process, and evidence. Do not overwrite formula columns S:T, W:Z, or AJ:AL. | AE4: Enter planned risk, execution, process, and evidence. Do not overwrite formula columns S:T, W:Z, or AJ:AL. | AF4: Enter planned risk, execution, process, and evidence. Do not overwrite formula columns S:T, W:Z, or AJ:AL. | AG4: Enter planned risk, execution, process, and evidence. Do not overwrite formula columns S:T, W:Z, or AJ:AL. | AH4: Enter planned risk, execution, process, and evidence. Do not overwrite formula columns S:T, W:Z, or AJ:AL. | AI4: Enter planned risk, execution, process, and evidence. Do not overwrite formula columns S:T, W:Z, or AJ:AL. | AJ4: Enter planned risk, execution, process, and evidence. Do not overwrite formula columns S:T, W:Z, or AJ:AL. | AK4: Enter planned risk, execution, process, and evidence. Do not overwrite formula columns S:T, W:Z, or AJ:AL. | AL4: Enter planned risk, execution, process, and evidence. Do not overwrite formula columns S:T, W:Z, or AJ:AL.
A5: Trade ID | B5: Date | C5: Account Mode | D5: Week | E5: Instrument | F5: Contract | G5: Session | H5: Direction | I5: Setup Version | J5: Regime | K5: Location | L5: Entry Time | M5: Entry Price | N5: Stop Price | O5: Target Price | P5: Exit Time | Q5: Exit Price | R5: Contracts | S5: Tick Size | T5: Tick Value | U5: Fees | V5: Slippage | W5: Gross P&L | X5: Net P&L | Y5: Initial Risk $ | Z5: R Multiple | AA5: MAE $ | AB5: MFE $ | AC5: Plan Followed | AD5: Process Grade | AE5: Hard Breach | AF5: Emotion/State | AG5: Screenshot Before | AH5: Screenshot After | AI5: Notes | AJ5: Cumulative R | AK5: Peak R | AL5: Drawdown R
S6: =IF(E6="","",IFERROR(VLOOKUP(E6,Lists!$A$5:$C$8,2,FALSE()),"")) | T6: =IF(E6="","",IFERROR(VLOOKUP(E6,Lists!$A$5:$C$8,3,FALSE()),"")) | W6: =IF(OR(M6="",Q6="",R6="",S6="",T6=""),"",IF(H6="Long",(Q6-M6)/S6*T6*R6,IF(H6="Short",(M6-Q6)/S6*T6*R6,""))) | X6: =IF(W6="","",W6-U6-V6) | Y6: =IF(OR(M6="",N6="",R6="",S6="",T6=""),"",ABS(M6-N6)/S6*T6*R6+U6+V6) | Z6: =IF(OR(X6="",Y6="",Y6=0),"",X6/Y6) | AJ6: =IF(B6="","",SUM($Z$6:Z6)) | AK6: =IF(AJ6="","",MAX($AJ$6:AJ6)) | AL6: =IF(AJ6="","",AJ6-AK6)
S7: =IF(E7="","",IFERROR(VLOOKUP(E7,Lists!$A$5:$C$8,2,FALSE()),"")) | T7: =IF(E7="","",IFERROR(VLOOKUP(E7,Lists!$A$5:$C$8,3,FALSE()),"")) | W7: =IF(OR(M7="",Q7="",R7="",S7="",T7=""),"",IF(H7="Long",(Q7-M7)/S7*T7*R7,IF(H7="Short",(M7-Q7)/S7*T7*R7,""))) | X7: =IF(W7="","",W7-U7-V7) | Y7: =IF(OR(M7="",N7="",R7="",S7="",T7=""),"",ABS(M7-N7)/S7*T7*R7+U7+V7) | Z7: =IF(OR(X7="",Y7="",Y7=0),"",X7/Y7) | AJ7: =IF(B7="","",SUM($Z$6:Z7)) | AK7: =IF(AJ7="","",MAX($AJ$6:AJ7)) | AL7: =IF(AJ7="","",AJ7-AK7)
S8: =IF(E8="","",IFERROR(VLOOKUP(E8,Lists!$A$5:$C$8,2,FALSE()),"")) | T8: =IF(E8="","",IFERROR(VLOOKUP(E8,Lists!$A$5:$C$8,3,FALSE()),"")) | W8: =IF(OR(M8="",Q8="",R8="",S8="",T8=""),"",IF(H8="Long",(Q8-M8)/S8*T8*R8,IF(H8="Short",(M8-Q8)/S8*T8*R8,""))) | X8: =IF(W8="","",W8-U8-V8) | Y8: =IF(OR(M8="",N8="",R8="",S8="",T8=""),"",ABS(M8-N8)/S8*T8*R8+U8+V8) | Z8: =IF(OR(X8="",Y8="",Y8=0),"",X8/Y8) | AJ8: =IF(B8="","",SUM($Z$6:Z8)) | AK8: =IF(AJ8="","",MAX($AJ$6:AJ8)) | AL8: =IF(AJ8="","",AJ8-AK8)
S9: =IF(E9="","",IFERROR(VLOOKUP(E9,Lists!$A$5:$C$8,2,FALSE()),"")) | T9: =IF(E9="","",IFERROR(VLOOKUP(E9,Lists!$A$5:$C$8,3,FALSE()),"")) | W9: =IF(OR(M9="",Q9="",R9="",S9="",T9=""),"",IF(H9="Long",(Q9-M9)/S9*T9*R9,IF(H9="Short",(M9-Q9)/S9*T9*R9,""))) | X9: =IF(W9="","",W9-U9-V9) | Y9: =IF(OR(M9="",N9="",R9="",S9="",T9=""),"",ABS(M9-N9)/S9*T9*R9+U9+V9) | Z9: =IF(OR(X9="",Y9="",Y9=0),"",X9/Y9) | AJ9: =IF(B9="","",SUM($Z$6:Z9)) | AK9: =IF(AJ9="","",MAX($AJ$6:AJ9)) | AL9: =IF(AJ9="","",AJ9-AK9)
S10: =IF(E10="","",IFERROR(VLOOKUP(E10,Lists!$A$5:$C$8,2,FALSE()),"")) | T10: =IF(E10="","",IFERROR(VLOOKUP(E10,Lists!$A$5:$C$8,3,FALSE()),"")) | W10: =IF(OR(M10="",Q10="",R10="",S10="",T10=""),"",IF(H10="Long",(Q10-M10)/S10*T10*R10,IF(H10="Short",(M10-Q10)/S10*T10*R10,""))) | X10: =IF(W10="","",W10-U10-V10) | Y10: =IF(OR(M10="",N10="",R10="",S10="",T10=""),"",ABS(M10-N10)/S10*T10*R10+U10+V10) | Z10: =IF(OR(X10="",Y10="",Y10=0),"",X10/Y10) | AJ10: =IF(B10="","",SUM($Z$6:Z10)) | AK10: =IF(AJ10="","",MAX($AJ$6:AJ10)) | AL10: =IF(AJ10="","",AJ10-AK10)
S11: =IF(E11="","",IFERROR(VLOOKUP(E11,Lists!$A$5:$C$8,2,FALSE()),"")) | T11: =IF(E11="","",IFERROR(VLOOKUP(E11,Lists!$A$5:$C$8,3,FALSE()),"")) | W11: =IF(OR(M11="",Q11="",R11="",S11="",T11=""),"",IF(H11="Long",(Q11-M11)/S11*T11*R11,IF(H11="Short",(M11-Q11)/S11*T11*R11,""))) | X11: =IF(W11="","",W11-U11-V11) | Y11: =IF(OR(M11="",N11="",R11="",S11="",T11=""),"",ABS(M11-N11)/S11*T11*R11+U11+V11) | Z11: =IF(OR(X11="",Y11="",Y11=0),"",X11/Y11) | AJ11: =IF(B11="","",SUM($Z$6:Z11)) | AK11: =IF(AJ11="","",MAX($AJ$6:AJ11)) | AL11: =IF(AJ11="","",AJ11-AK11)
S12: =IF(E12="","",IFERROR(VLOOKUP(E12,Lists!$A$5:$C$8,2,FALSE()),"")) | T12: =IF(E12="","",IFERROR(VLOOKUP(E12,Lists!$A$5:$C$8,3,FALSE()),"")) | W12: =IF(OR(M12="",Q12="",R12="",S12="",T12=""),"",IF(H12="Long",(Q12-M12)/S12*T12*R12,IF(H12="Short",(M12-Q12)/S12*T12*R12,""))) | X12: =IF(W12="","",W12-U12-V12) | Y12: =IF(OR(M12="",N12="",R12="",S12="",T12=""),"",ABS(M12-N12)/S12*T12*R12+U12+V12) | Z12: =IF(OR(X12="",Y12="",Y12=0),"",X12/Y12) | AJ12: =IF(B12="","",SUM($Z$6:Z12)) | AK12: =IF(AJ12="","",MAX($AJ$6:AJ12)) | AL12: =IF(AJ12="","",AJ12-AK12)
S13: =IF(E13="","",IFERROR(VLOOKUP(E13,Lists!$A$5:$C$8,2,FALSE()),"")) | T13: =IF(E13="","",IFERROR(VLOOKUP(E13,Lists!$A$5:$C$8,3,FALSE()),"")) | W13: =IF(OR(M13="",Q13="",R13="",S13="",T13=""),"",IF(H13="Long",(Q13-M13)/S13*T13*R13,IF(H13="Short",(M13-Q13)/S13*T13*R13,""))) | X13: =IF(W13="","",W13-U13-V13) | Y13: =IF(OR(M13="",N13="",R13="",S13="",T13=""),"",ABS(M13-N13)/S13*T13*R13+U13+V13) | Z13: =IF(OR(X13="",Y13="",Y13=0),"",X13/Y13) | AJ13: =IF(B13="","",SUM($Z$6:Z13)) | AK13: =IF(AJ13="","",MAX($AJ$6:AJ13)) | AL13: =IF(AJ13="","",AJ13-AK13)
S14: =IF(E14="","",IFERROR(VLOOKUP(E14,Lists!$A$5:$C$8,2,FALSE()),"")) | T14: =IF(E14="","",IFERROR(VLOOKUP(E14,Lists!$A$5:$C$8,3,FALSE()),"")) | W14: =IF(OR(M14="",Q14="",R14="",S14="",T14=""),"",IF(H14="Long",(Q14-M14)/S14*T14*R14,IF(H14="Short",(M14-Q14)/S14*T14*R14,""))) | X14: =IF(W14="","",W14-U14-V14) | Y14: =IF(OR(M14="",N14="",R14="",S14="",T14=""),"",ABS(M14-N14)/S14*T14*R14+U14+V14) | Z14: =IF(OR(X14="",Y14="",Y14=0),"",X14/Y14) | AJ14: =IF(B14="","",SUM($Z$6:Z14)) | AK14: =IF(AJ14="","",MAX($AJ$6:AJ14)) | AL14: =IF(AJ14="","",AJ14-AK14)
S15: =IF(E15="","",IFERROR(VLOOKUP(E15,Lists!$A$5:$C$8,2,FALSE()),"")) | T15: =IF(E15="","",IFERROR(VLOOKUP(E15,Lists!$A$5:$C$8,3,FALSE()),"")) | W15: =IF(OR(M15="",Q15="",R15="",S15="",T15=""),"",IF(H15="Long",(Q15-M15)/S15*T15*R15,IF(H15="Short",(M15-Q15)/S15*T15*R15,""))) | X15: =IF(W15="","",W15-U15-V15) | Y15: =IF(OR(M15="",N15="",R15="",S15="",T15=""),"",ABS(M15-N15)/S15*T15*R15+U15+V15) | Z15: =IF(OR(X15="",Y15="",Y15=0),"",X15/Y15) | AJ15: =IF(B15="","",SUM($Z$6:Z15)) | AK15: =IF(AJ15="","",MAX($AJ$6:AJ15)) | AL15: =IF(AJ15="","",AJ15-AK15)
S16: =IF(E16="","",IFERROR(VLOOKUP(E16,Lists!$A$5:$C$8,2,FALSE()),"")) | T16: =IF(E16="","",IFERROR(VLOOKUP(E16,Lists!$A$5:$C$8,3,FALSE()),"")) | W16: =IF(OR(M16="",Q16="",R16="",S16="",T16=""),"",IF(H16="Long",(Q16-M16)/S16*T16*R16,IF(H16="Short",(M16-Q16)/S16*T16*R16,""))) | X16: =IF(W16="","",W16-U16-V16) | Y16: =IF(OR(M16="",N16="",R16="",S16="",T16=""),"",ABS(M16-N16)/S16*T16*R16+U16+V16) | Z16: =IF(OR(X16="",Y16="",Y16=0),"",X16/Y16) | AJ16: =IF(B16="","",SUM($Z$6:Z16)) | AK16: =IF(AJ16="","",MAX($AJ$6:AJ16)) | AL16: =IF(AJ16="","",AJ16-AK16)
S17: =IF(E17="","",IFERROR(VLOOKUP(E17,Lists!$A$5:$C$8,2,FALSE()),"")) | T17: =IF(E17="","",IFERROR(VLOOKUP(E17,Lists!$A$5:$C$8,3,FALSE()),"")) | W17: =IF(OR(M17="",Q17="",R17="",S17="",T17=""),"",IF(H17="Long",(Q17-M17)/S17*T17*R17,IF(H17="Short",(M17-Q17)/S17*T17*R17,""))) | X17: =IF(W17="","",W17-U17-V17) | Y17: =IF(OR(M17="",N17="",R17="",S17="",T17=""),"",ABS(M17-N17)/S17*T17*R17+U17+V17) | Z17: =IF(OR(X17="",Y17="",Y17=0),"",X17/Y17) | AJ17: =IF(B17="","",SUM($Z$6:Z17)) | AK17: =IF(AJ17="","",MAX($AJ$6:AJ17)) | AL17: =IF(AJ17="","",AJ17-AK17)
... S205: =IF(E205="","",IFERROR(VLOOKUP(E205,Lists!$A$5:$C$8,2,FALSE()),"")) | T205: =IF(E205="","",IFERROR(VLOOKUP(E205,Lists!$A$5:$C$8,3,FALSE()),"")) | W205: =IF(OR(M205="",Q205="",R205="",S205="",T205=""),"",IF(H205="Long",(Q205-M205)/S205*T205*R205,IF(H205="Short",(M205-Q205)/S205*T205*R205,""))) | X205: =IF(W205="","",W205-U205-V205) | Y205: =IF(OR(M205="",N205="",R205="",S205="",T205=""),"",ABS(M205-N205)/S205*T205*R205+U205+V205) | Z205: =IF(OR(X205="",Y205="",Y205=0),"",X205/Y205) | AJ205: =IF(B205="","",SUM($Z$6:Z205)) | AK205: =IF(AJ205="","",MAX($AJ$6:AJ205)) | AL205: =IF(AJ205="","",AJ205-AK205)

Sheet Backtest
A1: Backtest & Out-of-Sample Log | B1: Backtest & Out-of-Sample Log | C1: Backtest & Out-of-Sample Log | D1: Backtest & Out-of-Sample Log | E1: Backtest & Out-of-Sample Log | F1: Backtest & Out-of-Sample Log | G1: Backtest & Out-of-Sample Log | H1: Backtest & Out-of-Sample Log | I1: Backtest & Out-of-Sample Log | J1: Backtest & Out-of-Sample Log | K1: Backtest & Out-of-Sample Log | L1: Backtest & Out-of-Sample Log | M1: Backtest & Out-of-Sample Log | N1: Backtest & Out-of-Sample Log | O1: Backtest & Out-of-Sample Log | P1: Backtest & Out-of-Sample Log | Q1: Backtest & Out-of-Sample Log | R1: Backtest & Out-of-Sample Log | S1: Backtest & Out-of-Sample Log | T1: Backtest & Out-of-Sample Log | U1: Backtest & Out-of-Sample Log | V1: Backtest & Out-of-Sample Log | W1: Backtest & Out-of-Sample Log | X1: Backtest & Out-of-Sample Log | Y1: Backtest & Out-of-Sample Log | Z1: Backtest & Out-of-Sample Log | AA1: Backtest & Out-of-Sample Log | AB1: Backtest & Out-of-Sample Log | AC1: Backtest & Out-of-Sample Log | AD1: Backtest & Out-of-Sample Log
A2: Use consecutive eligible sessions. Freeze setup rules before out-of-sample testing. Include costs and every valid occurrence. | B2: Use consecutive eligible sessions. Freeze setup rules before out-of-sample testing. Include costs and every valid occurrence. | C2: Use consecutive eligible sessions. Freeze setup rules before out-of-sample testing. Include costs and every valid occurrence. | D2: Use consecutive eligible sessions. Freeze setup rules before out-of-sample testing. Include costs and every valid occurrence. | E2: Use consecutive eligible sessions. Freeze setup rules before out-of-sample testing. Include costs and every valid occurrence. | F2: Use consecutive eligible sessions. Freeze setup rules before out-of-sample testing. Include costs and every valid occurrence. | G2: Use consecutive eligible sessions. Freeze setup rules before out-of-sample testing. Include costs and every valid occurrence. | H2: Use consecutive eligible sessions. Freeze setup rules before out-of-sample testing. Include costs and every valid occurrence. | I2: Use consecutive eligible sessions. Freeze setup rules before out-of-sample testing. Include costs and every valid occurrence. | J2: Use consecutive eligible sessions. Freeze setup rules before out-of-sample testing. Include costs and every valid occurrence. | K2: Use consecutive eligible sessions. Freeze setup rules before out-of-sample testing. Include costs and every valid occurrence. | L2: Use consecutive eligible sessions. Freeze setup rules before out-of-sample testing. Include costs and every valid occurrence. | M2: Use consecutive eligible sessions. Freeze setup rules before out-of-sample testing. Include costs and every valid occurrence. | N2: Use consecutive eligible sessions. Freeze setup rules before out-of-sample testing. Include costs and every valid occurrence. | O2: Use consecutive eligible sessions. Freeze setup rules before out-of-sample testing. Include costs and every valid occurrence. | P2: Use consecutive eligible sessions. Freeze setup rules before out-of-sample testing. Include costs and every valid occurrence. | Q2: Use consecutive eligible sessions. Freeze setup rules before out-of-sample testing. Include costs and every valid occurrence. | R2: Use consecutive eligible sessions. Freeze setup rules before out-of-sample testing. Include costs and every valid occurrence. | S2: Use consecutive eligible sessions. Freeze setup rules before out-of-sample testing. Include costs and every valid occurrence. | T2: Use consecutive eligible sessions. Freeze setup rules before out-of-sample testing. Include costs and every valid occurrence. | U2: Use consecutive eligible sessions. Freeze setup rules before out-of-sample testing. Include costs and every valid occurrence. | V2: Use consecutive eligible sessions. Freeze setup rules before out-of-sample testing. Include costs and every valid occurrence. | W2: Use consecutive eligible sessions. Freeze setup rules before out-of-sample testing. Include costs and every valid occurrence. | X2: Use consecutive eligible sessions. Freeze setup rules before out-of-sample testing. Include costs and every valid occurrence. | Y2: Use consecutive eligible sessions. Freeze setup rules before out-of-sample testing. Include costs and every valid occurrence. | Z2: Use consecutive eligible sessions. Freeze setup rules before out-of-sample testing. Include costs and every valid occurrence. | AA2: Use consecutive eligible sessions. Freeze setup rules before out-of-sample testing. Include costs and every valid occurrence. | AB2: Use consecutive eligible sessions. Freeze setup rules before out-of-sample testing. Include costs and every valid occurrence. | AC2: Use consecutive eligible sessions. Freeze setup rules before out-of-sample testing. Include costs and every valid occurrence. | AD2: Use consecutive eligible sessions. Freeze setup rules before out-of-sample testing. Include costs and every valid occurrence.
A4: Do not exclude a losing case retroactively. Mark Included = No only when a predeclared exclusion rule applies, and state it. | B4: Do not exclude a losing case retroactively. Mark Included = No only when a predeclared exclusion rule applies, and state it. | C4: Do not exclude a losing case retroactively. Mark Included = No only when a predeclared exclusion rule applies, and state it. | D4: Do not exclude a losing case retroactively. Mark Included = No only when a predeclared exclusion rule applies, and state it. | E4: Do not exclude a losing case retroactively. Mark Included = No only when a predeclared exclusion rule applies, and state it. | F4: Do not exclude a losing case retroactively. Mark Included = No only when a predeclared exclusion rule applies, and state it. | G4: Do not exclude a losing case retroactively. Mark Included = No only when a predeclared exclusion rule applies, and state it. | H4: Do not exclude a losing case retroactively. Mark Included = No only when a predeclared exclusion rule applies, and state it. | I4: Do not exclude a losing case retroactively. Mark Included = No only when a predeclared exclusion rule applies, and state it. | J4: Do not exclude a losing case retroactively. Mark Included = No only when a predeclared exclusion rule applies, and state it. | K4: Do not exclude a losing case retroactively. Mark Included = No only when a predeclared exclusion rule applies, and state it. | L4: Do not exclude a losing case retroactively. Mark Included = No only when a predeclared exclusion rule applies, and state it. | M4: Do not exclude a losing case retroactively. Mark Included = No only when a predeclared exclusion rule applies, and state it. | N4: Do not exclude a losing case retroactively. Mark Included = No only when a predeclared exclusion rule applies, and state it. | O4: Do not exclude a losing case retroactively. Mark Included = No only when a predeclared exclusion rule applies, and state it. | P4: Do not exclude a losing case retroactively. Mark Included = No only when a predeclared exclusion rule applies, and state it. | Q4: Do not exclude a losing case retroactively. Mark Included = No only when a predeclared exclusion rule applies, and state it. | R4: Do not exclude a losing case retroactively. Mark Included = No only when a predeclared exclusion rule applies, and state it. | S4: Do not exclude a losing case retroactively. Mark Included = No only when a predeclared exclusion rule applies, and state it. | T4: Do not exclude a losing case retroactively. Mark Included = No only when a predeclared exclusion rule applies, and state it. | U4: Do not exclude a losing case retroactively. Mark Included = No only when a predeclared exclusion rule applies, and state it. | V4: Do not exclude a losing case retroactively. Mark Included = No only when a predeclared exclusion rule applies, and state it. | W4: Do not exclude a losing case retroactively. Mark Included = No only when a predeclared exclusion rule applies, and state it. | X4: Do not exclude a losing case retroactively. Mark Included = No only when a predeclared exclusion rule applies, and state it. | Y4: Do not exclude a losing case retroactively. Mark Included = No only when a predeclared exclusion rule applies, and state it. | Z4: Do not exclude a losing case retroactively. Mark Included = No only when a predeclared exclusion rule applies, and state it. | AA4: Do not exclude a losing case retroactively. Mark Included = No only when a predeclared exclusion rule applies, and state it. | AB4: Do not exclude a losing case retroactively. Mark Included = No only when a predeclared exclusion rule applies, and state it. | AC4: Do not exclude a losing case retroactively. Mark Included = No only when a predeclared exclusion rule applies, and state it. | AD4: Do not exclude a losing case retroactively. Mark Included = No only when a predeclared exclusion rule applies, and state it.
A5: Case ID | B5: Date | C5: Instrument | D5: Setup Version | E5: Sample | F5: Direction | G5: Regime | H5: Location | I5: Entry | J5: Stop | K5: Target | L5: Exit | M5: Contracts | N5: Tick Size | O5: Tick Value | P5: Fees | Q5: Slippage | R5: Gross P&L | S5: Net P&L | T5: Initial Risk $ | U5: R Multiple | V5: MAE $ | W5: MFE $ | X5: Included | Y5: Exclusion Reason | Z5: Screenshot | AA5: Notes | AB5: Cumulative R | AC5: Peak R | AD5: Drawdown R
N6: =IF(C6="","",IFERROR(VLOOKUP(C6,Lists!$A$5:$C$8,2,FALSE()),"")) | O6: =IF(C6="","",IFERROR(VLOOKUP(C6,Lists!$A$5:$C$8,3,FALSE()),"")) | R6: =IF(OR(I6="",L6="",M6="",N6="",O6=""),"",IF(F6="Long",(L6-I6)/N6*O6*M6,IF(F6="Short",(I6-L6)/N6*O6*M6,""))) | S6: =IF(R6="","",R6-P6-Q6) | T6: =IF(OR(I6="",J6="",M6="",N6="",O6=""),"",ABS(I6-J6)/N6*O6*M6+P6+Q6) | U6: =IF(OR(S6="",T6="",T6=0),"",S6/T6) | AB6: =IF(OR(B6="",X6<>"Yes"),"",SUMIFS($U$6:U6,$X$6:X6,"Yes")) | AC6: =IF(AB6="","",MAX($AB$6:AB6)) | AD6: =IF(AB6="","",AB6-AC6)
N7: =IF(C7="","",IFERROR(VLOOKUP(C7,Lists!$A$5:$C$8,2,FALSE()),"")) | O7: =IF(C7="","",IFERROR(VLOOKUP(C7,Lists!$A$5:$C$8,3,FALSE()),"")) | R7: =IF(OR(I7="",L7="",M7="",N7="",O7=""),"",IF(F7="Long",(L7-I7)/N7*O7*M7,IF(F7="Short",(I7-L7)/N7*O7*M7,""))) | S7: =IF(R7="","",R7-P7-Q7) | T7: =IF(OR(I7="",J7="",M7="",N7="",O7=""),"",ABS(I7-J7)/N7*O7*M7+P7+Q7) | U7: =IF(OR(S7="",T7="",T7=0),"",S7/T7) | AB7: =IF(OR(B7="",X7<>"Yes"),"",SUMIFS($U$6:U7,$X$6:X7,"Yes")) | AC7: =IF(AB7="","",MAX($AB$6:AB7)) | AD7: =IF(AB7="","",AB7-AC7)
N8: =IF(C8="","",IFERROR(VLOOKUP(C8,Lists!$A$5:$C$8,2,FALSE()),"")) | O8: =IF(C8="","",IFERROR(VLOOKUP(C8,Lists!$A$5:$C$8,3,FALSE()),"")) | R8: =IF(OR(I8="",L8="",M8="",N8="",O8=""),"",IF(F8="Long",(L8-I8)/N8*O8*M8,IF(F8="Short",(I8-L8)/N8*O8*M8,""))) | S8: =IF(R8="","",R8-P8-Q8) | T8: =IF(OR(I8="",J8="",M8="",N8="",O8=""),"",ABS(I8-J8)/N8*O8*M8+P8+Q8) | U8: =IF(OR(S8="",T8="",T8=0),"",S8/T8) | AB8: =IF(OR(B8="",X8<>"Yes"),"",SUMIFS($U$6:U8,$X$6:X8,"Yes")) | AC8: =IF(AB8="","",MAX($AB$6:AB8)) | AD8: =IF(AB8="","",AB8-AC8)
N9: =IF(C9="","",IFERROR(VLOOKUP(C9,Lists!$A$5:$C$8,2,FALSE()),"")) | O9: =IF(C9="","",IFERROR(VLOOKUP(C9,Lists!$A$5:$C$8,3,FALSE()),"")) | R9: =IF(OR(I9="",L9="",M9="",N9="",O9=""),"",IF(F9="Long",(L9-I9)/N9*O9*M9,IF(F9="Short",(I9-L9)/N9*O9*M9,""))) | S9: =IF(R9="","",R9-P9-Q9) | T9: =IF(OR(I9="",J9="",M9="",N9="",O9=""),"",ABS(I9-J9)/N9*O9*M9+P9+Q9) | U9: =IF(OR(S9="",T9="",T9=0),"",S9/T9) | AB9: =IF(OR(B9="",X9<>"Yes"),"",SUMIFS($U$6:U9,$X$6:X9,"Yes")) | AC9: =IF(AB9="","",MAX($AB$6:AB9)) | AD9: =IF(AB9="","",AB9-AC9)
N10: =IF(C10="","",IFERROR(VLOOKUP(C10,Lists!$A$5:$C$8,2,FALSE()),"")) | O10: =IF(C10="","",IFERROR(VLOOKUP(C10,Lists!$A$5:$C$8,3,FALSE()),"")) | R10: =IF(OR(I10="",L10="",M10="",N10="",O10=""),"",IF(F10="Long",(L10-I10)/N10*O10*M10,IF(F10="Short",(I10-L10)/N10*O10*M10,""))) | S10: =IF(R10="","",R10-P10-Q10) | T10: =IF(OR(I10="",J10="",M10="",N10="",O10=""),"",ABS(I10-J10)/N10*O10*M10+P10+Q10) | U10: =IF(OR(S10="",T10="",T10=0),"",S10/T10) | AB10: =IF(OR(B10="",X10<>"Yes"),"",SUMIFS($U$6:U10,$X$6:X10,"Yes")) | AC10: =IF(AB10="","",MAX($AB$6:AB10)) | AD10: =IF(AB10="","",AB10-AC10)
N11: =IF(C11="","",IFERROR(VLOOKUP(C11,Lists!$A$5:$C$8,2,FALSE()),"")) | O11: =IF(C11="","",IFERROR(VLOOKUP(C11,Lists!$A$5:$C$8,3,FALSE()),"")) | R11: =IF(OR(I11="",L11="",M11="",N11="",O11=""),"",IF(F11="Long",(L11-I11)/N11*O11*M11,IF(F11="Short",(I11-L11)/N11*O11*M11,""))) | S11: =IF(R11="","",R11-P11-Q11) | T11: =IF(OR(I11="",J11="",M11="",N11="",O11=""),"",ABS(I11-J11)/N11*O11*M11+P11+Q11) | U11: =IF(OR(S11="",T11="",T11=0),"",S11/T11) | AB11: =IF(OR(B11="",X11<>"Yes"),"",SUMIFS($U$6:U11,$X$6:X11,"Yes")) | AC11: =IF(AB11="","",MAX($AB$6:AB11)) | AD11: =IF(AB11="","",AB11-AC11)
N12: =IF(C12="","",IFERROR(VLOOKUP(C12,Lists!$A$5:$C$8,2,FALSE()),"")) | O12: =IF(C12="","",IFERROR(VLOOKUP(C12,Lists!$A$5:$C$8,3,FALSE()),"")) | R12: =IF(OR(I12="",L12="",M12="",N12="",O12=""),"",IF(F12="Long",(L12-I12)/N12*O12*M12,IF(F12="Short",(I12-L12)/N12*O12*M12,""))) | S12: =IF(R12="","",R12-P12-Q12) | T12: =IF(OR(I12="",J12="",M12="",N12="",O12=""),"",ABS(I12-J12)/N12*O12*M12+P12+Q12) | U12: =IF(OR(S12="",T12="",T12=0),"",S12/T12) | AB12: =IF(OR(B12="",X12<>"Yes"),"",SUMIFS($U$6:U12,$X$6:X12,"Yes")) | AC12: =IF(AB12="","",MAX($AB$6:AB12)) | AD12: =IF(AB12="","",AB12-AC12)
N13: =IF(C13="","",IFERROR(VLOOKUP(C13,Lists!$A$5:$C$8,2,FALSE()),"")) | O13: =IF(C13="","",IFERROR(VLOOKUP(C13,Lists!$A$5:$C$8,3,FALSE()),"")) | R13: =IF(OR(I13="",L13="",M13="",N13="",O13=""),"",IF(F13="Long",(L13-I13)/N13*O13*M13,IF(F13="Short",(I13-L13)/N13*O13*M13,""))) | S13: =IF(R13="","",R13-P13-Q13) | T13: =IF(OR(I13="",J13="",M13="",N13="",O13=""),"",ABS(I13-J13)/N13*O13*M13+P13+Q13) | U13: =IF(OR(S13="",T13="",T13=0),"",S13/T13) | AB13: =IF(OR(B13="",X13<>"Yes"),"",SUMIFS($U$6:U13,$X$6:X13,"Yes")) | AC13: =IF(AB13="","",MAX($AB$6:AB13)) | AD13: =IF(AB13="","",AB13-AC13)
N14: =IF(C14="","",IFERROR(VLOOKUP(C14,Lists!$A$5:$C$8,2,FALSE()),"")) | O14: =IF(C14="","",IFERROR(VLOOKUP(C14,Lists!$A$5:$C$8,3,FALSE()),"")) | R14: =IF(OR(I14="",L14="",M14="",N14="",O14=""),"",IF(F14="Long",(L14-I14)/N14*O14*M14,IF(F14="Short",(I14-L14)/N14*O14*M14,""))) | S14: =IF(R14="","",R14-P14-Q14) | T14: =IF(OR(I14="",J14="",M14="",N14="",O14=""),"",ABS(I14-J14)/N14*O14*M14+P14+Q14) | U14: =IF(OR(S14="",T14="",T14=0),"",S14/T14) | AB14: =IF(OR(B14="",X14<>"Yes"),"",SUMIFS($U$6:U14,$X$6:X14,"Yes")) | AC14: =IF(AB14="","",MAX($AB$6:AB14)) | AD14: =IF(AB14="","",AB14-AC14)
N15: =IF(C15="","",IFERROR(VLOOKUP(C15,Lists!$A$5:$C$8,2,FALSE()),"")) | O15: =IF(C15="","",IFERROR(VLOOKUP(C15,Lists!$A$5:$C$8,3,FALSE()),"")) | R15: =IF(OR(I15="",L15="",M15="",N15="",O15=""),"",IF(F15="Long",(L15-I15)/N15*O15*M15,IF(F15="Short",(I15-L15)/N15*O15*M15,""))) | S15: =IF(R15="","",R15-P15-Q15) | T15: =IF(OR(I15="",J15="",M15="",N15="",O15=""),"",ABS(I15-J15)/N15*O15*M15+P15+Q15) | U15: =IF(OR(S15="",T15="",T15=0),"",S15/T15) | AB15: =IF(OR(B15="",X15<>"Yes"),"",SUMIFS($U$6:U15,$X$6:X15,"Yes")) | AC15: =IF(AB15="","",MAX($AB$6:AB15)) | AD15: =IF(AB15="","",AB15-AC15)
N16: =IF(C16="","",IFERROR(VLOOKUP(C16,Lists!$A$5:$C$8,2,FALSE()),"")) | O16: =IF(C16="","",IFERROR(VLOOKUP(C16,Lists!$A$5:$C$8,3,FALSE()),"")) | R16: =IF(OR(I16="",L16="",M16="",N16="",O16=""),"",IF(F16="Long",(L16-I16)/N16*O16*M16,IF(F16="Short",(I16-L16)/N16*O16*M16,""))) | S16: =IF(R16="","",R16-P16-Q16) | T16: =IF(OR(I16="",J16="",M16="",N16="",O16=""),"",ABS(I16-J16)/N16*O16*M16+P16+Q16) | U16: =IF(OR(S16="",T16="",T16=0),"",S16/T16) | AB16: =IF(OR(B16="",X16<>"Yes"),"",SUMIFS($U$6:U16,$X$6:X16,"Yes")) | AC16: =IF(AB16="","",MAX($AB$6:AB16)) | AD16: =IF(AB16="","",AB16-AC16)
N17: =IF(C17="","",IFERROR(VLOOKUP(C17,Lists!$A$5:$C$8,2,FALSE()),"")) | O17: =IF(C17="","",IFERROR(VLOOKUP(C17,Lists!$A$5:$C$8,3,FALSE()),"")) | R17: =IF(OR(I17="",L17="",M17="",N17="",O17=""),"",IF(F17="Long",(L17-I17)/N17*O17*M17,IF(F17="Short",(I17-L17)/N17*O17*M17,""))) | S17: =IF(R17="","",R17-P17-Q17) | T17: =IF(OR(I17="",J17="",M17="",N17="",O17=""),"",ABS(I17-J17)/N17*O17*M17+P17+Q17) | U17: =IF(OR(S17="",T17="",T17=0),"",S17/T17) | AB17: =IF(OR(B17="",X17<>"Yes"),"",SUMIFS($U$6:U17,$X$6:X17,"Yes")) | AC17: =IF(AB17="","",MAX($AB$6:AB17)) | AD17: =IF(AB17="","",AB17-AC17)
... N205: =IF(C205="","",IFERROR(VLOOKUP(C205,Lists!$A$5:$C$8,2,FALSE()),"")) | O205: =IF(C205="","",IFERROR(VLOOKUP(C205,Lists!$A$5:$C$8,3,FALSE()),"")) | R205: =IF(OR(I205="",L205="",M205="",N205="",O205=""),"",IF(F205="Long",(L205-I205)/N205*O205*M205,IF(F205="Short",(I205-L205)/N205*O205*M205,""))) | S205: =IF(R205="","",R205-P205-Q205) | T205: =IF(OR(I205="",J205="",M205="",N205="",O205=""),"",ABS(I205-J205)/N205*O205*M205+P205+Q205) | U205: =IF(OR(S205="",T205="",T205=0),"",S205/T205) | AB205: =IF(OR(B205="",X205<>"Yes"),"",SUMIFS($U$6:U205,$X$6:X205,"Yes")) | AC205: =IF(AB205="","",MAX($AB$6:AB205)) | AD205: =IF(AB205="","",AB205-AC205)

Sheet Observations
A1: Market Observation Log | B1: Market Observation Log | C1: Market Observation Log | D1: Market Observation Log | E1: Market Observation Log | F1: Market Observation Log | G1: Market Observation Log | H1: Market Observation Log | I1: Market Observation Log | J1: Market Observation Log | K1: Market Observation Log | L1: Market Observation Log | M1: Market Observation Log | N1: Market Observation Log | O1: Market Observation Log
A2: Record the hypothesis before revealing the outcome. Separate directly observed facts from interpretation. | B2: Record the hypothesis before revealing the outcome. Separate directly observed facts from interpretation. | C2: Record the hypothesis before revealing the outcome. Separate directly observed facts from interpretation. | D2: Record the hypothesis before revealing the outcome. Separate directly observed facts from interpretation. | E2: Record the hypothesis before revealing the outcome. Separate directly observed facts from interpretation. | F2: Record the hypothesis before revealing the outcome. Separate directly observed facts from interpretation. | G2: Record the hypothesis before revealing the outcome. Separate directly observed facts from interpretation. | H2: Record the hypothesis before revealing the outcome. Separate directly observed facts from interpretation. | I2: Record the hypothesis before revealing the outcome. Separate directly observed facts from interpretation. | J2: Record the hypothesis before revealing the outcome. Separate directly observed facts from interpretation. | K2: Record the hypothesis before revealing the outcome. Separate directly observed facts from interpretation. | L2: Record the hypothesis before revealing the outcome. Separate directly observed facts from interpretation. | M2: Record the hypothesis before revealing the outcome. Separate directly observed facts from interpretation. | N2: Record the hypothesis before revealing the outcome. Separate directly observed facts from interpretation. | O2: Record the hypothesis before revealing the outcome. Separate directly observed facts from interpretation.
A4: Hindsight contamination must be marked Yes if the original hypothesis was edited after seeing later price action. | B4: Hindsight contamination must be marked Yes if the original hypothesis was edited after seeing later price action. | C4: Hindsight contamination must be marked Yes if the original hypothesis was edited after seeing later price action. | D4: Hindsight contamination must be marked Yes if the original hypothesis was edited after seeing later price action. | E4: Hindsight contamination must be marked Yes if the original hypothesis was edited after seeing later price action. | F4: Hindsight contamination must be marked Yes if the original hypothesis was edited after seeing later price action. | G4: Hindsight contamination must be marked Yes if the original hypothesis was edited after seeing later price action. | H4: Hindsight contamination must be marked Yes if the original hypothesis was edited after seeing later price action. | I4: Hindsight contamination must be marked Yes if the original hypothesis was edited after seeing later price action. | J4: Hindsight contamination must be marked Yes if the original hypothesis was edited after seeing later price action. | K4: Hindsight contamination must be marked Yes if the original hypothesis was edited after seeing later price action. | L4: Hindsight contamination must be marked Yes if the original hypothesis was edited after seeing later price action. | M4: Hindsight contamination must be marked Yes if the original hypothesis was edited after seeing later price action. | N4: Hindsight contamination must be marked Yes if the original hypothesis was edited after seeing later price action. | O4: Hindsight contamination must be marked Yes if the original hypothesis was edited after seeing later price action.
A5: Observation ID | B5: Date | C5: Week | D5: Instrument | E5: Session | F5: Observation Type | G5: Regime | H5: Location | I5: Hypothesis Time | J5: Predeclared Hypothesis | K5: Confidence % | L5: Outcome | M5: Assigned Label | N5: Hindsight Contamination | O5: Screenshot / Notes

Sheet Study Log
A1: Study Log | B1: Study Log | C1: Study Log | D1: Study Log | E1: Study Log | F1: Study Log | G1: Study Log | H1: Study Log
A2: Record actual effort and evidence, not only completed readings. Time is an input; mastery is determined by the gates. | B2: Record actual effort and evidence, not only completed readings. Time is an input; mastery is determined by the gates. | C2: Record actual effort and evidence, not only completed readings. Time is an input; mastery is determined by the gates. | D2: Record actual effort and evidence, not only completed readings. Time is an input; mastery is determined by the gates. | E2: Record actual effort and evidence, not only completed readings. Time is an input; mastery is determined by the gates. | F2: Record actual effort and evidence, not only completed readings. Time is an input; mastery is determined by the gates. | G2: Record actual effort and evidence, not only completed readings. Time is an input; mastery is determined by the gates. | H2: Record actual effort and evidence, not only completed readings. Time is an input; mastery is determined by the gates.
A4: Use one row per study or practice block. Enter actual duration in minutes. Rows with Study ID EXAMPLE-001 are excluded from dashboard study hours. | B4: Use one row per study or practice block. Row 6 is an example and is excluded from dashboard study hours; overwrite or delete it when ready. | C4: Use one row per study or practice block. Row 6 is an example and is excluded from dashboard study hours; overwrite or delete it when ready. | D4: Use one row per study or practice block. Row 6 is an example and is excluded from dashboard study hours; overwrite or delete it when ready. | E4: Use one row per study or practice block. Row 6 is an example and is excluded from dashboard study hours; overwrite or delete it when ready. | F4: Use one row per study or practice block. Row 6 is an example and is excluded from dashboard study hours; overwrite or delete it when ready. | G4: Use one row per study or practice block. Row 6 is an example and is excluded from dashboard study hours; overwrite or delete it when ready. | H4: Use one row per study or practice block. Row 6 is an example and is excluded from dashboard study hours; overwrite or delete it when ready.
A5: Study ID | B5: Date | C5: Week | D5: Topic | E5: Completed | F5: Key Learning | G5: Open Question | H5: Evidence Link | I5: Duration (min)
A6: W01-1 | B6: 46258 | C6: 1 | D6: CFTC — Futures Market Basics NFA | E6: Yes | H6: See week 1 note
A7: W01-2 | B7: 46265 | C7: 1 | D7: CME – intro to future | E7: yes | H7: See week 1 note | I7: 60
A8: W01-3 | B8: 46265 | C8: 1 | D8: Part C | E8: yes | H8: See week 1 note | I8: 60
A9: W01-4 | B9: 46266 | C9: 1 | D9: Part D | E9: yes | H9: See week 1 note | I9: 60
A10: W01-5 | B10: 46267 | C10: 1 | D10: Install Windows 11; Review notions | E10: yes | I10: 60
A11: W01-6 | B11: 46268 | C11: 1 | D11: Part E | E11: yes | H11: Picture | I11: 60
A12: W01-7 | B12: 46267 | C12: 1 | D12: Book 01 | E12: yes | I12: 60
A13: W01-8 | B13: 46272 | C13: 1 | D13: Quiz F | E13: yes | H13: See week 1 note | I13: 120
A14: W02-1 | B14: 46281 | C14: 2 | D14: Answer initial questions from GPT about risk | E14: Partial | I14: 60
A15: W02-2 | B15: 46282 | C15: 2 | D15: Answer question about risk | E15: Yes | I15: 30
A16: W02-3 | B16: 46283 | C16: 2 | D16: Part A | E16: Yes | F16: Notional value, calculate tick value and total $ | H16: See week 2 assignment. | I16: 60
A17: W02-4 | B17: 46284 | C17: 2 | D17: Part B | E17: Yes | F17: P&L from fills | H17: See week 2 assignment. | I17: 30
A18: W02-5 | B18: 46285 | C18: 2 | D18: Part C | E18: Yes | F18: Planned risk and costs | H18: See week 2 assignment. | I18: 60
A19: W02-6 | B19: 46286 | C19: 2 | D19: Part D | E19: Yes | F19: Spread and cost | H19: See week 2 assignment. | I19: 90
A20: W02-7 | B20: 46287 | C20: 2 | D20: Lab | E20: Yes | H20: See week 2 assignment. | I20: 60
A21: W02-8 | B21: 46288 | C21: 2 | D21: Quiz | E21: yes | I21: 40
A22: W02-9 | B22: 46288 | C22: 2 | D22: Part 7 | E22: Yes | H22: See week 2 assignment. | I22: 30
A23: W03-1 | B23: 46293 | C23: 3 | D23: Part A and B | E23: Yes | F23: Concensus, actual for MES MGC MCL | H23: See week 3 assignment | I23: 60
A24: W03-2 | B24: 46294 | C24: 3 | D24: Fiche MES CASE 1 | E24: Yes | F24: Hypothese, observation, drawing on sierra chart. | H24: See research week 3 01-mes.md | I24: 60
A25: W03-3 | B25: 46295 | C25: 3 | D25: Fiche MES CASE 2 | E25: Yes | F25: Donnée de l’emploi au États-Unis | H25: See research week 3 02-mes.md | I25: 60
A26: W03-4 | B26: 46300 | C26: 3 | D26: Fiche MES CASE 3 | E26: Yes | F26: Donnée des PPI au États-Unis | H26: See research week 3 03-mes.md | I26: 30
A27: W03-5 | B27: 46301 | C27: 3 | D27: Fiche MGC CASE 4 | E27: Yes | F27: Donnée de Taux de la fed. | H27: See research week 3 04-mgc.md | I27: 60
A28: W03-6 | B28: 46302 | C28: 3 | D28: Fiche MCL CASE 5 | E28: YES | F28: Donnée de variation des stocks de baril de pétrol | H28: See research week 3 05-mcl.md | I28: 30
A29: W03-7 | B29: 46305 | C29: 3 | D29: Quiz | E29: Yes | F29: Quiz recap | H29: Quiz | I29: 60

Sheet Lists
A1: Reference Lists | B1: Reference Lists | C1: Reference Lists | D1: Reference Lists | E1: Reference Lists | F1: Reference Lists
A2: Editable lists support dropdowns. Contract values were verified from CME sources on 2026-08-23; recheck before use. | B2: Editable lists support dropdowns. Contract values were verified from CME sources on 2026-08-23; recheck before use. | C2: Editable lists support dropdowns. Contract values were verified from CME sources on 2026-08-23; recheck before use. | D2: Editable lists support dropdowns. Contract values were verified from CME sources on 2026-08-23; recheck before use. | E2: Editable lists support dropdowns. Contract values were verified from CME sources on 2026-08-23; recheck before use. | F2: Editable lists support dropdowns. Contract values were verified from CME sources on 2026-08-23; recheck before use.
A4: Instrument | B4: Tick Size | C4: Tick Value | D4: Point/Unit Value | E4: Contract summary | F4: Official source
A5: MES | B5: 0.25 | C5: 1.25 | D5: 5 | E5: $5 × S&P 500 Index | F5: https://www.cmegroup.com/markets/equities/sp/micro-e-mini-sandp-500.contractSpecs.html
A6: MNQ | B6: 0.25 | C6: 0.5 | D6: 2 | E6: $2 × Nasdaq-100 Index | F6: https://www.cmegroup.com/markets/equities/nasdaq/micro-e-mini-nasdaq-100.contractSpecs.html
A7: MGC | B7: 0.1 | C7: 1 | D7: 10 | E7: 10 troy ounces | F7: https://www.cmegroup.com/markets/metals/precious/e-micro-gold.contractSpecs.html
A8: MCL | B8: 0.01 | C8: 1 | D8: 100 | E8: 100 barrels | F8: https://www.cmegroup.com/markets/energy/crude-oil/micro-wti-crude-oil.contractSpecs.html
A10: Account Modes | B10: Direction | C10: Regime | D10: Yes/No | E10: Process Grade | F10: Sample
A11: Observation | B11: Long | C11: Balance | D11: Yes | E11: A | F11: In-sample
A12: Replay Sim | B12: Short | C12: Transition | D12: No | E12: B | F12: Out-of-sample
A13: Server Sim | C13: Imbalance | E13: C
A14: Paper Broker Sim | C14: Trend | E14: D
A15: Live | C15: Unknown | E15: F

Sheet README
A1: How to Use This Workbook | B1: How to Use This Workbook | C1: How to Use This Workbook | D1: How to Use This Workbook | E1: How to Use This Workbook | F1: How to Use This Workbook | G1: How to Use This Workbook | H1: How to Use This Workbook
A2: The workbook supports the Academy curriculum; the Markdown files remain the learning and policy source of truth. | B2: The workbook supports the Academy curriculum; the Markdown files remain the learning and policy source of truth. | C2: The workbook supports the Academy curriculum; the Markdown files remain the learning and policy source of truth. | D2: The workbook supports the Academy curriculum; the Markdown files remain the learning and policy source of truth. | E2: The workbook supports the Academy curriculum; the Markdown files remain the learning and policy source of truth. | F2: The workbook supports the Academy curriculum; the Markdown files remain the learning and policy source of truth. | G2: The workbook supports the Academy curriculum; the Markdown files remain the learning and policy source of truth. | H2: The workbook supports the Academy curriculum; the Markdown files remain the learning and policy source of truth.
A4: Workflow | B4: Workflow | C4: Workflow | D4: Workflow | E4: Workflow | F4: Workflow | G4: Workflow | H4: Workflow
A5: Step | B5: Action | C5: Where | D5: Input rule | E5: Formula rule | F5: Evidence | G5: Frequency | H5: Safety
A6: 1 | B6: Plan the session | C6: Markdown session plan | D6: Write before the market unfolds | E6: None | F6: Saved plan | G6: Every observed/traded session | H6: No account action if mode is uncertain
A7: 2 | B7: Record study | C7: Study Log | D7: One row per work block | E7: Dashboard sums hours | F7: Evidence link | G7: Every work block | H7: Do not equate hours with competence
A8: 3 | B8: Record observations | C8: Observations | D8: No hindsight edits | E8: Dashboard counts dated rows | F8: Screenshot/notes | G8: As assigned | H8: Mark contamination honestly
A9: 4 | B9: Record historical cases | C9: Backtest | D9: Consecutive eligible cases | E9: P&L, risk, R, equity, drawdown | F9: Before/after image | G9: Weeks 14–16+ | H9: Freeze OOS rules
A10: 5 | B10: Record completed trades | C10: Trades | D10: One completed trade per row | E10: P&L, risk, R, equity, drawdown | F10: Before/after image | G10: Replay and simulation | H10: Never overwrite formulas
A12: Color and formula conventions | B12: Color and formula conventions | C12: Color and formula conventions | D12: Color and formula conventions | E12: Color and formula conventions | F12: Color and formula conventions | G12: Color and formula conventions | H12: Color and formula conventions
A13: Color | B13: Meaning | C13: Example | D13: Action
A14: Blue text | B14: Editable user input | C14: Trade entry price | D14: Enter or update
A15: Gray fill / black text | B15: Formula-derived | C15: R Multiple | D15: Do not overwrite
A16: Amber | B16: Attention or provisional input | C16: Risk assumption | D16: Review deliberately
A17: Red | B17: Safety/process exception | C17: Hard breach | D17: Stop and review
A19: Formula definitions | B19: Formula definitions | C19: Formula definitions | D19: Formula definitions | E19: Formula definitions | F19: Formula definitions | G19: Formula definitions | H19: Formula definitions
A20: Metric | B20: Definition
A21: Gross P&L | B21: Direction-adjusted tick movement × tick value × contracts
A22: Net P&L | B22: Gross P&L − fees − slippage
A23: Initial Risk | B23: Absolute entry-to-stop tick distance × tick value × contracts + fees + slippage
A24: R Multiple | B24: Net P&L ÷ Initial Risk
A25: Drawdown R | B25: Cumulative R − prior peak cumulative R
A27: Warning: Futures trading is leveraged and can produce losses greater than the initial deposit. Simulation results can differ materially from live fills and behavior. This workbook does not authorize live trading. | B27: Warning: Futures trading is leveraged and can produce losses greater than the initial deposit. Simulation results can differ materially from live fills and behavior. This workbook does not authorize live trading. | C27: Warning: Futures trading is leveraged and can produce losses greater than the initial deposit. Simulation results can differ materially from live fills and behavior. This workbook does not authorize live trading. | D27: Warning: Futures trading is leveraged and can produce losses greater than the initial deposit. Simulation results can differ materially from live fills and behavior. This workbook does not authorize live trading. | E27: Warning: Futures trading is leveraged and can produce losses greater than the initial deposit. Simulation results can differ materially from live fills and behavior. This workbook does not authorize live trading. | F27: Warning: Futures trading is leveraged and can produce losses greater than the initial deposit. Simulation results can differ materially from live fills and behavior. This workbook does not authorize live trading. | G27: Warning: Futures trading is leveraged and can produce losses greater than the initial deposit. Simulation results can differ materially from live fills and behavior. This workbook does not authorize live trading. | H27: Warning: Futures trading is leveraged and can produce losses greater than the initial deposit. Simulation results can differ materially from live fills and behavior. This workbook does not authorize live trading.
A28: Warning: Futures trading is leveraged and can produce losses greater than the initial deposit. Simulation results can differ materially from live fills and behavior. This workbook does not authorize live trading. | B28: Warning: Futures trading is leveraged and can produce losses greater than the initial deposit. Simulation results can differ materially from live fills and behavior. This workbook does not authorize live trading. | C28: Warning: Futures trading is leveraged and can produce losses greater than the initial deposit. Simulation results can differ materially from live fills and behavior. This workbook does not authorize live trading. | D28: Warning: Futures trading is leveraged and can produce losses greater than the initial deposit. Simulation results can differ materially from live fills and behavior. This workbook does not authorize live trading. | E28: Warning: Futures trading is leveraged and can produce losses greater than the initial deposit. Simulation results can differ materially from live fills and behavior. This workbook does not authorize live trading. | F28: Warning: Futures trading is leveraged and can produce losses greater than the initial deposit. Simulation results can differ materially from live fills and behavior. This workbook does not authorize live trading. | G28: Warning: Futures trading is leveraged and can produce losses greater than the initial deposit. Simulation results can differ materially from live fills and behavior. This workbook does not authorize live trading. | H28: Warning: Futures trading is leveraged and can produce losses greater than the initial deposit. Simulation results can differ materially from live fills and behavior. This workbook does not authorize live trading.
A29: Warning: Futures trading is leveraged and can produce losses greater than the initial deposit. Simulation results can differ materially from live fills and behavior. This workbook does not authorize live trading. | B29: Warning: Futures trading is leveraged and can produce losses greater than the initial deposit. Simulation results can differ materially from live fills and behavior. This workbook does not authorize live trading. | C29: Warning: Futures trading is leveraged and can produce losses greater than the initial deposit. Simulation results can differ materially from live fills and behavior. This workbook does not authorize live trading. | D29: Warning: Futures trading is leveraged and can produce losses greater than the initial deposit. Simulation results can differ materially from live fills and behavior. This workbook does not authorize live trading. | E29: Warning: Futures trading is leveraged and can produce losses greater than the initial deposit. Simulation results can differ materially from live fills and behavior. This workbook does not authorize live trading. | F29: Warning: Futures trading is leveraged and can produce losses greater than the initial deposit. Simulation results can differ materially from live fills and behavior. This workbook does not authorize live trading. | G29: Warning: Futures trading is leveraged and can produce losses greater than the initial deposit. Simulation results can differ materially from live fills and behavior. This workbook does not authorize live trading. | H29: Warning: Futures trading is leveraged and can produce losses greater than the initial deposit. Simulation results can differ materially from live fills and behavior. This workbook does not authorize live trading.
